LICENSE
README.md
setup.py
config/__init__.py
config/global_config.py
group_center/__init__.py
group_center/user_env.py
group_center/user_tools.py
group_center/client/__init__.py
group_center/client/machine/__init__.py
group_center/client/machine/ssh_helper.py
group_center/client/machine/ssh_helper_tui.py
group_center/client/machine/user_manager.py
group_center/client/machine/feature/__init__.py
group_center/client/machine/feature/add_user.py
group_center/client/machine/feature/ssh/__init__.py
group_center/client/machine/feature/ssh/authorized_keys_file.py
group_center/client/machine/feature/ssh/key_pair_file.py
group_center/client/machine/feature/ssh/ssh_helper_linux.py
group_center/client/machine/feature/ssh/ssh_key_pair_manager.py
group_center/client/machine/feature/ssh/ssh_keys_utils.py
group_center/client/toolkit/__init__.py
group_center/client/toolkit/fix_conda_bin_shiban.py
group_center/client/toolkit/feature/__init__.py
group_center/client/toolkit/feature/conda.py
group_center/client/user/__init__.py
group_center/client/user/shell_message.py
group_center/client/user/windows_terminal.py
group_center/client/user/datatype/__init__.py
group_center/client/user/datatype/linux_user.py
group_center/client/user/datatype/user_info.py
group_center/client/user/datatype/webhook.py
group_center/config/__init__.py
group_center/config/global_config.py
group_center/config/version.py
group_center/core/__init__.py
group_center/core/config_core.py
group_center/core/group_center_encrypt.py
group_center/core/group_center_machine.py
group_center/core/path.py
group_center/core/feature/__init__.py
group_center/core/feature/backup_user_file.py
group_center/core/feature/custom_client_message.py
group_center/core/feature/machine_message.py
group_center/core/feature/remote_config.py
group_center/example/__init__.py
group_center/example/rtsp/__init__.py
group_center/example/rtsp/cv2_generate_video.py
group_center/example/rtsp/cv2_push.py
group_center/example/rtsp/pillow_push.py
li_group_center.egg-info/PKG-INFO
li_group_center.egg-info/SOURCES.txt
li_group_center.egg-info/dependency_links.txt
li_group_center.egg-info/entry_points.txt
li_group_center.egg-info/requires.txt
li_group_center.egg-info/top_level.txt
