Metadata-Version: 2.4
Name: li_group_center
Version: 2.6.1
Summary: Group Center Tools
Home-page: https://github.com/a645162/group-center-client
Author: Haomin Kong
Author-email: a645162@gmail.com
License: GPLv3
Requires-Python: >=3.6
License-File: LICENSE
Requires-Dist: typing-extensions
Requires-Dist: urllib3
Requires-Dist: requests
Requires-Dist: termcolor>=1.0.0
Requires-Dist: colorama>=0.4.0; platform_system == "Windows"
Requires-Dist: windows-curses>=2.2.0; platform_system == "Windows"
Requires-Dist: psutil
Requires-Dist: rich>=12.0.0
Requires-Dist: tqdm
Dynamic: author
Dynamic: author-email
Dynamic: description
Dynamic: description-content-type
Dynamic: home-page
Dynamic: license
Dynamic: license-file
Dynamic: requires-dist
Dynamic: requires-python
Dynamic: summary
